Metadata-Version: 2.1
Name: prometheus-alert-model
Version: 1.0.0
Summary: Pydantic model of the Prometheus Alertmanager alert payload
Home-page: https://github.com/trallnag/prometheus-alert-model-for-python
License: Apache-2.0
Keywords: prometheus,alertmanager,alerting,pydantic
Author: Tim Schwenke
Author-email: tim.and.trallnag+code@gmail.com
Requires-Python: >=3.7,<4.0
Classifier: License :: OSI Approved :: Apache Software License
Classifier: Programming Language :: Python :: 3
Classifier: Programming Language :: Python :: 3.7
Classifier: Programming Language :: Python :: 3.8
Classifier: Programming Language :: Python :: 3.9
Requires-Dist: pydantic (>=1.7.2,<2.0.0)
Requires-Dist: typing-extensions (>=3.7.4,<4.0.0)
Project-URL: Repository, https://github.com/trallnag/prometheus-alert-model-for-python
